README.md
setup.py
winky/__init__.py
winky/database_mysql.py
winky/database_oracle.py
winky/database_postgre.py
winky/http_message.py
winky/http_stub.py
winky/new_project.py
winky/ssl.py
winky/template_json.py
winky/template_text.py
winky/template_xml.py
winky.egg-info/PKG-INFO
winky.egg-info/SOURCES.txt
winky.egg-info/dependency_links.txt
winky.egg-info/requires.txt
winky.egg-info/top_level.txt