Metadata-Version: 2.1
Name: winky
Version: 1.15.3
Summary: API Test Framework
Home-page: https://bitbucket.org/alborov/winky
Author: Zaur Alborov
Author-email: alborov.z@gmail.com
License: MIT
Platform: UNKNOWN
